{
  "type": "tcots-witcher:alchemy_table",
  "base": {
    "item": "tcots-witcher:dragons_dream"
  },
  "category": "bombs_oils",
  "ingredient_counters": [
    1,
    2,
    1,
    2,
    2
  ],
  "ingredients": [
    {
      "item": "tcots-witcher:stammelfords_dust"
    },
    {
      "item": "minecraft:glowstone_dust"
    },
    {
      "item": "minecraft:amethyst_shard"
    },
    {
      "item": "minecraft:oxeye_daisy"
    },
    {
      "item": "tcots-witcher:bryonia"
    }
  ],
  "order": 0.45999983,
  "result": {
    "item": "tcots-witcher:dragons_dream_enhanced"
  }
}